2024 - Implementacion de un procesador según la arqutectura rv32i de RISC-V/Codigo fuente/rv32i/dataPath/PC/PC.v
/*1) registro contador de programa
nombre: PC
ent: clk, pcNext(32)
sal: pc(32)
*/
module PC (
	input wire clk,				//reloj
	input wire rst,				//reset
	input wire [31:0] pcNext,	//siguiente valor del PC
	output reg [31:0] pc		//valor actual del PC
);

	always @(posedge clk or posedge rst) begin
		if (rst) begin
			pc <= 32'h0000_0000;
		end else
		begin
		pc <= pcNext;
		end
	end
endmodule

2024 - Implementacion de un procesador según la arqutectura rv32i de RISC-V/Codigo fuente/rv32i/dataPath/PC/PC_tb.v
`timescale 1ns / 1ps
`define DUMPSTR(x) `"x.vcd"

module PC_tb;

    // Señales de prueba
    reg clk;                  // Reloj
    reg rst;                  // Reset
    reg [31:0] pcNext;       // Valor siguiente del PC
    wire [31:0] pc;          // Valor actual del PC

    // Instanciación del módulo PC
    PC pc_module (
        .clk(clk),
        .rst(rst),
        .pcNext(pcNext),
        .pc(pc)
    );

    // Generador de reloj
    initial begin
        clk = 0; // Inicializar el reloj en 0
    end
    
    always #5 clk = ~clk; // Reloj de 10 ns de periodo

    // Proceso de prueba
    initial begin
		$dumpfile(`DUMPSTR(`VCD_OUTPUT));
        $dumpvars(0, PC_tb);
        
        // Inicialización de señales
        rst = 1; // Activar reset
        #10; // Esperar 10 unidades de tiempo
        rst = 0;

        // Esperar un ciclo de reloj antes de cambiar pcNext
        #10; 
        pcNext = 32'h00000001; // Cambiar pcNext
        #10; // Esperar otro ciclo
        pcNext = 32'h00000002; // Cambiar pcNext
        #10; // Esperar otro ciclo
        pcNext = 32'h00000003; // Cambiar pcNext
        #10; // Esperar otro ciclo

        // Finalizar la simulación
        $finish;
    end

endmodule

2024 - Implementacion de un procesador según la arqutectura rv32i de RISC-V/Codigo fuente/rv32i/dataPath/PC/PC_tb.vcd
$date
	Mon Nov 11 19:26:56 2024
$end
$version
	Icarus Verilog
$end
$timescale
	1ps
$end
$scope module PC_tb $end
$var wire 32 ! pc [31:0] $end
$var reg 1 " clk $end
$var reg 32 # pcNext [31:0] $end
$var reg 1 $ rst $end
$scope module pc_module $end
$var wire 1 " clk $end
$var wire 32 % pcNext [31:0] $end
$var wire 1 $ rst $end
$var reg 32 & pc [31:0] $end
$upscope $end
$upscope $end
$enddefinitions $end
#0
$dumpvars
b0 &
bx %
1$
bx #
0"
b0 !
$end
#5000
1"
#10000
0"
0$
#15000
bx !
bx &
1"
#20000
0"
b1 #
b1 %
#25000
b1 !
b1 &
1"
#30000
0"
b10 #
b10 %
#35000
b10 !
b10 &
1"
#40000
0"
b11 #
b11 %
#45000
b11 !
b11 &
1"
