2024 - Implementacion de un procesador según la arqutectura rv32i de RISC-V/Codigo fuente/rv32i/UC/aluDeco/aluDeco.v
module aluDeco(
	input wire op, f7, 
	input wire[2:0] f3,
	input wire[1:0] aluOp,
	output reg[2:0] aluControl
	);
	
	always @(*) begin
		// Inicializar aluControl a un valor por defecto
        aluControl = 3'bxxx; // Valor indefinido al inicio
		case(aluOp)
			2'b00 : aluControl = 3'b000; //instruction: lw, sw
			2'b01 : aluControl = 3'b001; //beq
			2'b10 :
				begin
					case(f3)
						3'b000 :
							begin
								if (op == 1'b0 && f7 == 1'b0) aluControl = 3'b000;
								if (op == 1'b0 && f7 == 1'b1) aluControl = 3'b000;
								if (op == 1'b1 && f7 == 1'b0) aluControl = 3'b000;
								if (op == 1'b1 && f7 == 1'b1) aluControl = 3'b001;
							end
						3'b010 : aluControl = 3'b101; //slt
						3'b110 : aluControl = 3'b011; //or
						3'b111 : aluControl = 3'b010; //and
					endcase
				end
			default : aluControl = 3'bxxx; // Código indefinido
		endcase
	end
endmodule

2024 - Implementacion de un procesador según la arqutectura rv32i de RISC-V/Codigo fuente/rv32i/UC/aluDeco/aluDeco_tb.v
`timescale 1ns / 1ps
`define DUMPSTR(x) `"x.vcd`"

module aluDeco_tb;

    // Parámetros de la prueba
    reg op;
    reg f7;
    reg [2:0] f3;
    reg [1:0] aluOp;
    wire [2:0] aluControl;

    // Instanciación del módulo bajo prueba
    aluDeco uut (
        .op(op),
        .f7(f7),
        .f3(f3),
        .aluOp(aluOp),
        .aluControl(aluControl)
    );

    // Procedimiento de prueba
    initial begin
        $dumpfile(`DUMPSTR(`VCD_OUTPUT));  // Archivo para almacenar los resultados de la simulación
        $dumpvars(0, aluDeco_tb);               // Volcado de todas las variables
        // Mostrar los resultados
        $monitor("Time: %0dns | op: %b | f7: %b | f3: %b | aluOp: %b | aluControl: %b",
                 $time, op, f7, f3, aluOp, aluControl);
        
        // Probar combinaciones significativas
        // Test 1: lw, sw (aluOp = 00)
        aluOp = 2'b00; f3 = 3'b000; op = 0; f7 = 0; #10; // Expect aluControl = 000
        
        // Test 2: beq (aluOp = 01)
        aluOp = 2'b01; f3 = 3'b000; op = 0; f7 = 0; #10; // Expect aluControl = 001
        
        // Test 3: R-type with f3 = 000
        aluOp = 2'b10; f3 = 3'b000;
        op = 0; f7 = 0; #10; // Expect aluControl = 000
        op = 1; f7 = 0; #10; // Expect aluControl = 000
        op = 0; f7 = 1; #10; // Expect aluControl = 000
        op = 1; f7 = 1; #10; // Expect aluControl = 001
        
        // Test 4: R-type with f3 = 010 (slt)
        f3 = 3'b010; op = 0; f7 = 0; aluOp = 2'b10; #10; // Expect aluControl = 101
        
        // Test 5: R-type with f3 = 110 (or)
        f3 = 3'b110; op = 0; f7 = 0; #10; // Expect aluControl = 011
        
        // Test 6: R-type with f3 = 111 (and)
        f3 = 3'b111; op = 0; f7 = 0; #10; // Expect aluControl = 010
        
        // Test 7: R-type with f3 = 101 (don't care for op and f7)
        f3 = 3'b101; aluOp = 2'b10; op = 0; f7 = 0; #10; // Expect aluControl = xxx

        // Test 8: R-type with f3 = 001 (don't care for op)
        f3 = 3'b001; aluOp = 2'b10; op = 0; f7 = 1; #10; // Expect aluControl = xxx

        // Finalizar la simulación
        $finish;
    end

endmodule

2024 - Implementacion de un procesador según la arqutectura rv32i de RISC-V/Codigo fuente/rv32i/UC/aluDeco/aluDeco_tb.vcd
$date
	Wed Nov 06 16:12:23 2024
$end
$version
	Icarus Verilog
$end
$timescale
	1ps
$end
$scope module aluDeco_tb $end
$var wire 3 ! aluControl [2:0] $end
$var reg 2 " aluOp [1:0] $end
$var reg 3 # f3 [2:0] $end
$var reg 1 $ f7 $end
$var reg 1 % op $end
$scope module uut $end
$var wire 2 & aluOp [1:0] $end
$var wire 3 ' f3 [2:0] $end
$var wire 1 $ f7 $end
$var wire 1 % op $end
$var reg 3 ( aluControl [2:0] $end
$upscope $end
$upscope $end
$enddefinitions $end
#0
$dumpvars
b0 (
b0 '
b0 &
0%
0$
b0 #
b0 "
b0 !
$end
#10000
b1 !
b1 (
b1 "
b1 &
#20000
b0 !
b0 (
b10 "
b10 &
#30000
b0 !
b0 (
1%
#40000
b0 !
b0 (
1$
0%
#50000
b1 !
b1 (
1%
#60000
b101 !
b101 (
0$
0%
b10 #
b10 '
#70000
b11 !
b11 (
b110 #
b110 '
#80000
b10 !
b10 (
b111 #
b111 '
#90000
bx !
bx (
b101 #
b101 '
#100000
1$
b1 #
b1 '
