2024 - Implementacion de un procesador según la arqutectura rv32i de RISC-V/Codigo fuente/rv32i/UC/aluDeco/aluDeco.v
module aluDeco(
	input wire op, f7, 
	input wire[2:0] f3,
	input wire[1:0] aluOp,
	output reg[2:0] aluControl
	);
	
	always @(*) begin
		// Inicializar aluControl a un valor por defecto
        aluControl = 3'bxxx; // Valor indefinido al inicio
		case(aluOp)
			2'b00 : aluControl = 3'b000; //instruction: lw, sw
			2'b01 : aluControl = 3'b001; //beq
			2'b10 :
				begin
					case(f3)
						3'b000 :
							begin
								if (op == 1'b0 && f7 == 1'b0) aluControl = 3'b000;
								if (op == 1'b0 && f7 == 1'b1) aluControl = 3'b000;
								if (op == 1'b1 && f7 == 1'b0) aluControl = 3'b000;
								if (op == 1'b1 && f7 == 1'b1) aluControl = 3'b001;
							end
						3'b010 : aluControl = 3'b101; //slt
						3'b110 : aluControl = 3'b011; //or
						3'b111 : aluControl = 3'b010; //and
					endcase
				end
			default : aluControl = 3'bxxx; // Código indefinido
		endcase
	end
endmodule

2024 - Implementacion de un procesador según la arqutectura rv32i de RISC-V/Codigo fuente/rv32i/UC/mainDeco/mainDeco.v
module mainDeco(
    input wire [6:0] op,
    output reg branch,
    output reg [1:0] resSrc,
    output reg memWrite,
    output reg aluSrc,
    output reg [1:0] inmSrc,
    output reg regWrite,
    output reg [1:0] aluOp,
    output reg jump
);
always @(*) begin
    case (op)
        3 : //load word
            begin
                regWrite = 1'b1;
                inmSrc = 2'b00;
                aluSrc = 1'b1;
                memWrite = 1'b0;
                resSrc = 2'b01;
                branch = 1'b0;
                aluOp = 2'b00;
                jump = 1'b0;
            end
        35 : //store word
            begin
                regWrite = 1'b0;
                inmSrc = 2'b01;
                aluSrc = 1'b1;
                memWrite = 1'b1;
                resSrc = 2'bxx;
                branch = 1'b0;
                aluOp = 2'b00;
                jump = 1'b0;
            end
        51 : //R-type
            begin
                regWrite = 1'b1;
                inmSrc = 2'bxx;
                aluSrc = 1'b0;
                memWrite = 1'b0;
                resSrc = 2'b00;
                branch = 1'b0;
                aluOp = 2'b10;
                jump = 1'b0;
            end
        99 : //beq
            begin
                regWrite = 1'b0;
                inmSrc = 2'b10;
                aluSrc = 1'b0;
                memWrite = 1'b0;
                resSrc = 2'bxx;
                branch = 1'b1;
                aluOp = 2'b01;
                jump = 1'b0;
            end
        19 : //addi
            begin
                regWrite = 1'b1;
                inmSrc = 2'b00;
                aluSrc = 1'b1;
                memWrite = 1'b0;
                resSrc = 2'b00;
                branch = 1'b0;
                aluOp = 2'b10;
                jump = 1'b0;
            end
        111 : //jal
            begin
                regWrite = 1'b1;
                inmSrc = 2'b11;
                aluSrc = 1'bx;
                memWrite = 1'b0;
                resSrc = 2'b10;
                branch = 1'b0;
                aluOp = 2'bxx;
                jump = 1'b1;
            end
        default :
             begin
                regWrite = 1'bx;
                inmSrc = 2'bxx;
                aluSrc = 1'bx;
                memWrite = 1'bx;
                resSrc = 2'bxx;
                branch = 1'bx;
                aluOp = 2'bxx;
                jump = 1'bx;
             end
    endcase
end
endmodule

2024 - Implementacion de un procesador según la arqutectura rv32i de RISC-V/Codigo fuente/rv32i/UC/UC.v
`ifdef FROM_RV32I
    `include "UC/mainDeco/mainDeco.v"
    `include "UC/aluDeco/aluDeco.v"
`else
    `include "mainDeco/mainDeco.v"
    `include "aluDeco/aluDeco.v"
`endif


module UC(
	input wire zero,
	input wire [6:0] op,
	input wire [2:0] f3,
	input wire f7,
	
	output reg pcSrc,
	output wire [1:0] resSrc,
	output wire memWrite,
	output wire [2:0] aluControl,
	output wire aluSrc,
	output wire [1:0] immSrc,
	output wire regWrite
);

wire [1:0] aluOp;
wire branch;
wire jump;

always @(*) begin
	pcSrc = (zero & branch)|jump;
end

mainDeco mainDeco_0 (
        .op(op),
		.branch(branch),
		.resSrc(resSrc),
		.memWrite(memWrite),
		.aluSrc(aluSrc),
		.inmSrc(immSrc),
		.regWrite(regWrite),
		.aluOp(aluOp),
		.jump(jump)
    );
	
aluDeco aluDeco_0 (
        .f3(f3),
		.op(op[5]),
		.f7(f7),
		.aluOp(aluOp),
		.aluControl(aluControl)
    );
	
endmodule

2024 - Implementacion de un procesador según la arqutectura rv32i de RISC-V/Codigo fuente/rv32i/UC/UC_tb.v
`timescale 1ns / 1ps
`define DUMPSTR(x) `"x.vcd`"

module UC_tb;

    // Señales de prueba
    reg zero;
    reg [6:0] op;
    reg [2:0] f3;
    reg f7;
    
    wire pcSrc;
    wire [1:0] resSrc;
    wire memWrite;
    wire [2:0] aluControl;
    wire aluSrc;
    wire [1:0] immSrc;
    wire regWrite;

    // Instanciación del módulo UC
    UC uc_inst (
        .zero(zero),
        .op(op),
        .f3(f3),
        .f7(f7),
        .pcSrc(pcSrc),
        .resSrc(resSrc),
        .memWrite(memWrite),
        .aluControl(aluControl),
        .aluSrc(aluSrc),
        .immSrc(immSrc),
        .regWrite(regWrite)
    );

    // Proceso de prueba
    initial begin
        $dumpfile(`DUMPSTR(`VCD_OUTPUT));  // Archivo para almacenar los resultados de la simulación
        $dumpvars(0, UC_tb); 
        // Inicializar señales
        zero = 0;
        op = 7'b0000000;
        f3 = 3'b000;
        f7 = 0;

        // Estimulos de prueba
        #10;
        op = 7'b1100011; // Branch instruction
        zero = 1;
        #10;
        zero = 0;
        #10;
        op = 7'b1101111; // Jump instruction
        #10;
        op = 7'b0000011; // Load instruction
        #10;
        op = 7'b0100011; // Store instruction
        #10;
        op = 7'b0110011; // R-type instruction
        f3 = 3'b000;
        f7 = 1;
        #10;
        op = 7'b0010011; // I-type instruction
        f3 = 3'b000;
        f7 = 0;
        #10;

        // Finalizar la simulación
        $finish;
    end

    // Monitor para observar las señales
    initial begin
        $monitor("Time = %0t, zero = %b, op = %b, f3 = %b, f7 = %b, pcSrc = %b, resSrc = %b, memWrite = %b, aluControl = %b, aluSrc = %b, immSrc = %b, regWrite = %b",
                 $time, zero, op, f3, f7, pcSrc, resSrc, memWrite, aluControl, aluSrc, immSrc, regWrite);
    end

endmodule

2024 - Implementacion de un procesador según la arqutectura rv32i de RISC-V/Codigo fuente/rv32i/UC/UC_tb.vcd
$date
	Wed Nov 06 17:09:39 2024
$end
$version
	Icarus Verilog
$end
$timescale
	1ps
$end
$scope module UC_tb $end
$var wire 2 ! resSrc [1:0] $end
$var wire 1 " regWrite $end
$var wire 1 # pcSrc $end
$var wire 1 $ memWrite $end
$var wire 2 % immSrc [1:0] $end
$var wire 1 & aluSrc $end
$var wire 3 ' aluControl [2:0] $end
$var reg 3 ( f3 [2:0] $end
$var reg 1 ) f7 $end
$var reg 7 * op [6:0] $end
$var reg 1 + zero $end
$scope module uc_inst $end
$var wire 3 , f3 [2:0] $end
$var wire 1 ) f7 $end
$var wire 7 - op [6:0] $end
$var wire 1 + zero $end
$var wire 2 . resSrc [1:0] $end
$var wire 1 " regWrite $end
$var wire 1 $ memWrite $end
$var wire 1 / jump $end
$var wire 2 0 immSrc [1:0] $end
$var wire 1 1 branch $end
$var wire 1 & aluSrc $end
$var wire 2 2 aluOp [1:0] $end
$var wire 3 3 aluControl [2:0] $end
$var reg 1 # pcSrc $end
$scope module aluDeco_0 $end
$var wire 3 4 f3 [2:0] $end
$var wire 1 ) f7 $end
$var wire 1 5 op $end
$var wire 2 6 aluOp [1:0] $end
$var reg 3 7 aluControl [2:0] $end
$upscope $end
$scope module mainDeco_0 $end
$var wire 7 8 op [6:0] $end
$var reg 2 9 aluOp [1:0] $end
$var reg 1 & aluSrc $end
$var reg 1 1 branch $end
$var reg 2 : inmSrc [1:0] $end
$var reg 1 / jump $end
$var reg 1 $ memWrite $end
$var reg 1 " regWrite $end
$var reg 2 ; resSrc [1:0] $end
$upscope $end
$upscope $end
$upscope $end
$enddefinitions $end
#0
$dumpvars
bx ;
bx :
bx 9
b0 8
bx 7
bx 6
05
b0 4
bx 3
bx 2
x1
bx 0
x/
bx .
b0 -
b0 ,
0+
b0 *
0)
b0 (
bx '
x&
bx %
x$
x#
x"
bx !
$end
#10000
b1 '
b1 3
b1 7
1#
15
0/
b1 2
b1 6
b1 9
11
0$
0&
b10 %
b10 0
b10 :
0"
1+
b1100011 *
b1100011 -
b1100011 8
#20000
0#
0+
#30000
bx '
bx 3
bx 7
1#
1/
bx 2
bx 6
bx 9
01
b10 !
b10 .
b10 ;
x&
b11 %
b11 0
b11 :
1"
b1101111 *
b1101111 -
b1101111 8
#40000
0#
b0 '
b0 3
b0 7
05
0/
b0 2
b0 6
b0 9
b1 !
b1 .
b1 ;
1&
b0 %
b0 0
b0 :
b11 *
b11 -
b11 8
#50000
b0 '
b0 3
b0 7
15
bx !
bx .
bx ;
1$
b1 %
b1 0
b1 :
0"
b100011 *
b100011 -
b100011 8
#60000
b1 '
b1 3
b1 7
b10 2
b10 6
b10 9
b0 !
b0 .
b0 ;
0$
0&
bx %
bx 0
bx :
1"
1)
b110011 *
b110011 -
b110011 8
#70000
b0 '
b0 3
b0 7
05
1&
b0 %
b0 0
b0 :
0)
b10011 *
b10011 -
b10011 8
